{"id":"Buzzsprout-811003","title":"#1.19: Ignatius Ig Nobel","date":"2018-09-24","audio_url":"https://sphinx.acast.com/p/open/s/65ba62a1f83c2300169e5234/e/Buzzsprout-811003/media.mp3","episode_url":"https://shows.acast.com/videnskabeligt-udfordret/episodes/65ba62aa98ef180017b6e8d7","description":"I kender ham som groupien fra afsnit to. Manden med over tusind gange så meget! Frederik Bartholdy Neergaard! Ugens gæst har medbragt en artikel, der er så meget i Spækbrættets ånd, at det er et under, at den ikke har været med i tre andre afsnit. Høns. Kan se forskel på grimme og smukke mennesker. Mark og Robin har hver især forberedt en hyldest til den store Ig Nobel-pris ceremoni, hvor usandsynligt videnskab takkes og belønnes hvert eneste år. Og Flemming vil have en kæleræv, der kan tisse i hans kaffe.","duration":"1:16:20","episode_number":1,"image_url":"https://assets.pippa.io/shows/65ba62a1f83c2300169e5234/65ba62aa98ef180017b6e8d7.jpg","transcript":null,"dyrfakt":null,"listener_question":null}