{"id":"Buzzsprout-12338578","title":"#114: En forening mellem videnskab og journalistik (m. Vanvittig Verdenshistorie)","date":"2023-02-27","audio_url":"https://sphinx.acast.com/p/open/s/65ba62a1f83c2300169e5234/e/Buzzsprout-12338578/media.mp3","episode_url":"https://shows.acast.com/videnskabeligt-udfordret/episodes/65ba62aa98ef180017b6e7ec","description":"I dag har vi besøg af nogle meget vigtige gæster: Vanvittig Verdenshistorie. Og når vi har talt sammen, så plejer Alexander altid at sige: ”Mark og Flemming de ved jo hvad de snakker om, de har lange uddannelser og publiceret forskning til at bakke dem op”. Men sandheden er, at når vi laver vores podcast, så er vi faktisk på ret dybt vand. Ikke på grund af videnskaben (selvom det ofte også er tilfældet), men fordi vi faktisk ikke har nogen formel træning i formidling. Overhovedet. Så i dag vil vi sammen med Peter og Alexander, der har træning og uddannelse i formidling og journalistik, finde ud af hvordan vi mest effektivt kommunikerer videnskab.","duration":"1:25:36","episode_number":114,"image_url":"https://assets.pippa.io/shows/65ba62a1f83c2300169e5234/65ba62aa98ef180017b6e7ec.jpg","transcript":null}