{"id":"Buzzsprout-9546209","title":"#046: Vand er bedst uden diarré (John Snow)","date":"2021-11-15","audio_url":"https://sphinx.acast.com/p/open/s/65ba62a1f83c2300169e5234/e/Buzzsprout-9546209/media.mp3","episode_url":"https://shows.acast.com/videnskabeligt-udfordret/episodes/65ba62aa98ef180017b6e831","description":"Det 18. og 19. århundrede bød for den vestlige verden på en industrialisering, der trak flere og flere mennesker ind i byer hvor de bogstaveligt talt boede og levede i deres eget lort. Og tilfældigvis så blev folk på denne tid også meget syge, men af en eller anden grund skulle der en radikalt tænkende læge til, før det gik op for folk at der var en sammenhæng mellem afføring og sygdom. Lyt med når Mark fortæller om John Snow og hvordan han opklarede mysteriet om Londons kolera-epidemier og fik overbevist verdenen om at Kolera bliver spredt gennem vand, så vi kunne holde op med at drikke diarré. Mange, mange tak John.","duration":"1:18:54","episode_number":46,"image_url":"https://assets.pippa.io/shows/65ba62a1f83c2300169e5234/65ba62aa98ef180017b6e831.jpg","transcript":"London var under en rimelig stor forøgelse. Der kom mange mennesker til. Der var mange mennesker der. Så de der cesspools, som man basically havde i hver eneste gårdhave, de var ikke store nok. Så de blev overfyldt. Siger du, at jorden ikke hurtigt nok kunne sluge deres fucking lort? Der var så mange mennesker i London, at jorden ikke kunne sluge deres lort. Udfordret er en dansk videnskabskomik podcast medværterne Mark og Flemming. Vi bringer en advarsel. Den følgende podcast handler om vanvittig videnskab. Al forskningen, der præsenteres, er 100% ægte og udført af professionelle. Mark og Flemming står ikke til ansvar for eventuelle misforståelser, men minder jer om, at I altid har ret. Husk at være dum. Hej og velkommen til videnskabeligt Udfordret, din brug til vanvittig videnskab, hvor vi forklarer videnskab, så alle kan forstå det. Jeg er gårdejer Flemming Damgaard Nielsen. Jeg er dårlig luft, Mark Løn. Dårlig luft. Det er det samme, som går af jer på tåsingen, tror jeg. Det tror jeg også. Det var næsten lidt jazzagtigt, Flemming. Det var virkelig. Det var en god energi, den kunne jeg godt lide. Jamen, jeg prøver at forny mig. Så er det ikke det samme hver eneste gang? Ej, det tror jeg ikke. Det er ikke altid den der Radio 4-stem, du kommer med. Øh, nej. Altså, der er variationer på den. Jeg tror bare, at man skal have sådan lidt mere kulturel øregang end dig for at kunne fornemme forskellen. Jeg kan ikke høre forskellen overhovedet. I tonefaldet. Det er også fordi, du ikke har trænet lige så meget som jeg i stemmeføring. Ja. Okay. Hvad betyder stemmeføring? Det betyder, at hvis du bøuser ved bordet, så får du en lussing af din mor. Det er stemmeføring. Der har været meget stemmeføring hjemme hos os. Så derfor er vi så gode til at lave podcast, Mark. Mark, hvorfor har du varm luft i dag? Jeg har ikke varm luft, jeg har dårlig luft. Du har dårlig luft? Jeg har simpelthen dårlig luft. Og det er fordi, at i dagens afsnit skal vi tale om faderen af et forskningsfelt, der bliver kaldt for epidemiologi. Udfordret er en dansk videnskabskomik podcast medværterne Mark og Flemming. Ikke Game of Thrones, Flemming. Jeg kunne se, at du var allerede lige på vej. Ej, men Mark, han styrer jo også et udbrud af zombie-virus, jo. Ja, det er rigtigt. Så der er alligevel noget der. Okay, fair nok, fair nok, fair nok. Det er næste samme, men ikke helt, fordi det er faktisk ikke virus, vi skal snakke om i dag, men det er rimelig zombie-agtigt. Men det er mest, fordi det er cholera, og cholera er altid zombie-agtigt. Det er numse-zombie-sygdommen. Så i dag skal vi tale om Jon Snow, og vi skal tale om, hvordan han opklarede mysteriet om Londons koleraepidemier, og fik overbevist verden om, at kolera bliver spredt gennem vand, så vi kan holde op med at drikke diarré. Det må virkelig have været en radikal handling dengang, at skulle overbevise folk om, at de ikke skulle drikke hinandens afføring. Nu sidder du og joker med det, men helt seriøst. Det var virkelig, virkelig, virkelig svært. Det var sådan, altså prøv at tænke på, hvor vrede folk er i dag over, at de skal have en vaccine. Prøv at tænke på, hvor vrede de vil blive, hvis de fik at vide, at de ikke må drikke hinandens afføring. Det var faktisk, jeg har det ikke med afsnit, jeg skal godt sige det her. Det var faktisk, det største problem for folk, det var, at de kunne ikke lide tanken om, at sygdom skulle spredes fra numsen og ind igennem munden og igennem tarmsystemet og så ud af numsen igen. Det gav ikke mening, eller hvad? Nej, de kunne ikke lide tanken om det. Altså, de vidste godt, at de drak diarævand. Men de kunne ikke lide tanken om, at de skulle drikke diarævand. Så de lå bare være med at tænke på det, og tænke på, at det gav sygdom. Det er fandme smart. Men også fucking, fucking dumt. Lifehack lige der. Er du træt af at drikke diaræ? Bare lad være med at tænke på det. Det er ikke diaræ, det er bare vand. Bare rolig. Det er risvand, Flemming. Udfordret er en dansk videnskabskomik podcast medværterne Mark og Flemming. Så folk havde protesteret imod, og ikke om at drikke deres arveføring? Nej, ja. Og jeres, der ville være der. Og der ville være mediedækning, og folk ville gøre det ude for en samling rådhuspladser. Jeg har slet ikke tvivl om det. Åh, ja. Flemming. Må jeg fortælle dig om Jon Snow og kodere? Ja, tak. Det 18. og det 19. århundrede, det bød for den vestlige verden på en industrialisering, der træk flere og flere mennesker ind i byer, hvor man så kom ind i byerne og så boede folk under de mest uhumske forhold, man kan tænke sig. Det var ligesom nødvendigt, folk de skulle ud væk fra landet af, de skulle ind i byerne, fordi der var arbejde inde i byerne, men når man så kom ind i byerne, så var der en million andre mennesker, og hvad sker der, når en million andre mennesker, de er på samme sted, Flemming? Det bliver ulækkert. Det bliver rigtig, rigtig ulækkert. Det bliver faktisk virkelig, virkelig ulækkert. Specielt under en tid, hvor det var det moderne kloaksystem. Det havde rimelig lang udsigt inden det almindelige hjem. Åh nej. Og prøv at tænke på at bo i storbyen uden at have kloaksystemer. Jeg prøver lige at tænke på det en gang. Det kan være, at du kan forklare for mig, hvordan det rent faktisk så ud. Det kan være, at du bare kan beskrive dig til, hvordan det så ud, Flemming. Altså nu ved jeg jo på landet, inden der var kloaksystemer, der gik man bare ud af skæd ved grisene. Det gjorde min oldefar og min farfar, og det var en meget stolt familietradition, du ved. Bare tage vis med, og så sætter sig i handen, og så skider man. Altså når grisene kan, så kan vi fem også. Ja, det er også rigtigt. Men jeg tænker ikke, altså hvis man bor i en lille bitte lejlighed inde i København, Jeg tror ikke, folk har en svinestil, de går ud og skider i. Nej, altså det er ikke så anstændigt, du ved, at sidde og skide for en andre folk. Det er jo folk, der bor inde i storbyerne, Flemming. De er jo høje mennesker, de er jo anstændige mennesker, ikke? Så de skider sikkert bare... De skider bare en kop og smider det ud af vinduet. Ja! Mark, er det rigtigt? Det er virkelig ikke langt fra. Så det gik rimelig hurtigt op for folk, at hvis man ligesom tilløb alle at skide i Randestenen, så blev London fyldt op med lort. Altså bogstaveligt talt. Så det man gjorde i stedet for, det var at man skid i en kop eller en spand, og så tog man den her spand, og så tømte man den ned i sådan nogle kæmpe store afføringsbrønde. Også det, der hedder cesspools. Det er en gylletank for menneskelort. Ja, det er en gylletank for menneskelort. Og det var simpelthen, ideen det var så, at de her cesspools, de var kæmpestore, altså det var en brønd til lort. Og man havde lavet dem kæmpestore, for vi vidste godt, at folk havde rigtig, rigtig meget lort, de skulle af med. Så man hældte ligesom sit lort ud og sit tis ud i de her afføringsbrønde, og så ventede man på, at det trækte ned i jorden igennem. Men nu ender man hyggeligt ud af. Nej! Årh, det er ulækkert! Årh! Og det stinker! Altså, menneskelort er så fucking klamt. Ja, ja. Og hvis du så blander det med tis også, så kan jeg fortælle dig, så er det slet ikke sjovt. Altså, en ting er lugten af en gylletank. Men altså, jeg har stået ved siden af bjerg af lort, der er jo sådan flere meter højt. Nej, det er altså... Altså, menneskelort. Min far... Mark og Flemming er en dansk videnskabskomik podcast medværterne Mark og Flemming. Altså, det lugtede værre end noget andet, jeg nogensinde lugtede. Fuck, det er ulækkert. Og det var virkeligheden for alle mennesker, der boede i London. Og det var faktisk så slemt, Flemming, fordi man ventede på, at det trækte ned i jorden. Og så kunne man ligesom fylde noget mere på, ikke? Men London var under en rimelig stor forøgelse. Der kom mange mennesker til, der var mange mennesker der. Så de der cesspools, som man basically havde i hver eneste gårdhave, de var ikke store nok, så de blev overfyldt. Siger du, at jorden ikke hurtigt nok kunne sluge deres fucking lort? Der var så mange mennesker i London, at jorden ikke kunne sluge deres lort. No fucking shit. Altså, jeg elsker bare den der mentalitet med, hvis vi bare lægger det ned i det her hul, så løser det sig selv. Ja. Udfordret er en dansk videnskabskomik podcast medværterne Mark og Flemming. Det er lidt det, vi gør med radioaktivt affald. Hvad skal vi gøre med det her affald? Vi putter det bare ind i et stort hul. Jeg tror, at det er det, der er det poni. Jeg tror, at i Sverige ligger et kæmpestort hul ude i havet, at man har gravet ned i en klippe eller sådan noget, og man smider det ned i nu. Hvor man smider radioaktivt affald ind i og venter på, at det bare hengår. Ja, man venter bare på, at det løser sig selv. Ja, det er så menneskeligt. Hvor er det bare virkelig, virkelig menneskeligt. Mark og Flemming er en dansk videnskabskomik podcast medværterne Mark og Flemming. Der forsøgte man at sætte fokus på at undgå forurening af den. Den var så klam på det her tidspunkt allerede, at man var sådan Det kan godt være, at folk skal lade være med at kaste os lort hud i floden. Jeg synes, den er ved at være så tyk, at jeg kan gå på den. Jeg er Jesus. De blev der ikke gjort specielt meget ved. Og det var ikke fordi, at der var nogen, der overholdte den regel. Det var ikke fordi, at det blev håndhævet på nogen som helst måde. Så folk blev bare ved med at kaste os lort ud. Dansk videnskabskomik podcast medværterne Mark og Flemming. Altså det smukkeste dyr, naturen har skabt. Mennesket har simpelthen menneskeskabt noget, som de selv syntes var så klamt, at de kaldte det, eller de sagde, at det lugtede af død. Man havde med skot til temsen på det her tidspunkt, man kaldte den Father Thames, altså temsen faderen, eller far temsen, som skulle forestille at være sådan en rigtig, rigtig, rigtig ulækker trold. Udfordret er en dansk videnskabskomik podcast medværterne Mark og Flemming. Dansk videnskabeligt Udfordret er en dansk videnskabeligt podcast medværterne Mark og Flemming. Mark og Flemming. Knugen er så voldsomt et dyr, at hvis man bare lader dem gå naturligt ude på savannen, så går de til så store mængder, at de slår sig selv ihjel, fordi de ikke har mere mad. Og at de så dør, det gør, at de ikke kan komme til mere, så dør der endnu flere. Så knugerne de æder så meget, at de bare bliver så gigantisk, altså milliardmasse af knuger. Og det betyder, at de så dør til sådan en milliardmasse af døde knuger, og så ødelægger det hele økosystemet hver sæson. Det er også meget smukt. Ja, men det syge er så, at økosystemet ligesom har tilpasset sig til at knure, når de dør. Og så på den måde, så er det faktisk en del af økosystemet nu. Det er ret syret. Og det er ret fucked up. Det er ret fucked up. Så er det knusæson igen. Ja, præcis. Jeg tror, at problemet med mennesker og grunden til, at vi ikke er knure, det er nok fordi, at vi gør for mange ting for hurtigt, og vi ændrer for meget i vores adfærd. Og så har du tænkt på, at hvis vores teknologiske udvikling var lidt langsommere, så kunne økosystemet på jorden forberede sig på, at nu begynder de at lukke en hel masse CO2 ud igen. Yes, præcis. Nu kommer der næste masseudrydelse, og så ved jeg, så kunne de hele tiden komme sig. Så kommer vi tilbage til middelalderen, og så skal vi ligesom udvikle os til at gøre det en gang til. Det er 100% det, jeg tænker. Hvem ved, hvad der er sket om en million år? Der tror jeg, vi udvikler os alt for hurtigt. Vi ødelægger bare jordklodsen ved at knipse. Teknobarbarene rider rundt på et musaurus. Så der er både rigtig mange folk i London, de skid ned i store huller, eller de kaster deres lort ned i store huller, eller ud i floden. Og foruden ligesom at have rimelig dårlig kloakadgang, så havde man også rimelig dårlig vandtilførsel, vandforsyning. Så det folk, de ligesom havde vand, det var det, de kunne pumpe op gennem brønde. Og det vand, der kom i de brønde, det var enten vand fra Temsen eller vand fra kilder, der lå lidt opstrøms af Temsen. Som er gravet ned i den jord, som de i forvejen prøver at få al deres afføring til at sive ind i. Ja ja, Flemming, men deres håndværk, det er jo et godt håndværk, det er jo tæt. Det er jo tæt håndværk, sådan! Men så kommer der ikke noget vand i brønden, hvis grundvandet ikke kan sive ind i den? Jamen jeg tror, at de har faktisk ikke brugt grundvand i de fleste tilfælde. Hvad? Det er en brønd, hvor de så har lavet en vandledning til, så de kunne pumpe vand op af den her vandledning. Hvad? Så nogle få af dem har været grundvandsbrønde, men fordi der var så mange mennesker, skulle de have flere brønder, så var det nødt til at pumpe vand op fra andre steder. Hvor har man mest vand? Hvor har man mest ferskvand i London? I Thamesen. Så der var faktisk vandværkere på det her tidspunkt her, de fik så, de pumpede vandet fra temsen op til de her brønde her, og det var så det folk de drak af. Og det man gjorde, det var ligesom man gik ud, og så tog man sit vand med, og så pumpede man noget vand op, og så havde man det vand til hele dagen. Eller også så tog man hele kam af, og så havde man vand til en uge eller sådan noget. Alt det for mange der var. Hold kæft hvor er det ulækkert og dumt. Men det vidste folk jo. Det putter sådan en Brexit i et nyt perspektiv. Men det var jo ikke ulækker Flemming, det var jo, det var bare vand. Hvad er problemet? Skal vand ikke være brunt og fyldt Og majskerner. Og majskerner. Det tror jeg nok, det skal. Skal det ikke have sådan en sjov tyk konsistens? Skal det ikke have sådan en skorpe på overfladen? Hvor gross. Åh shit, mand. Tilfældigvis så rammer de her meget dårlige kloakforhold og den her utrolig dårlige lugt, de rammer sammen med, at London var konstant ramt af sygdomsudbrud. Og specifikt så stifter man bekendtskab med en af vores gamle kendinger, cholera. Og det gjorde man i 1831, hvor den første af mange choleraepidemier i London, eller i England, startede. Og lige en hurtig opsummering til dem, der ikke har hørt vores choleraafsnit. Så cholera er en bakterie, eller en bakterieinfektion, der giver dig så hårdt diaræ, at du tømmer det meste af din krop for vand på 24 timer. Det er stort set det. Og den eneste måde, du sådan reelt kan overleve på, det er bare at drikke så meget vand, at du når at få mere vand ind, end du får vand ud. Saltvand, Flemming. Ja, for ellers så mister du dig lidt salt også. Præcis, og det går ikke. Det er ikke så rart en sygdom, hvis man skulle være i tvivl. Så bare ridde tønskedsbyen. På det her tidspunkt her, der vidste man ikke, at man skulle drikke vand, og man vidste slet ikke, at man skulle drikke saltvand. Og da man ikke kendte til nogle behandlinger, så døde rigtig mange mennesker af kolader. Så det var faktisk en dødsdom, når du fik kolader. På samme tidspunkt i 1831, der var John Snow, vores protagonist, han var lige ved at færdiggøre sin medicinske lærlingetid. Og han var ved at være klar til at starte på sin rigtige medicinske studier. Han havde været lærling et stykke tid, og nu skulle han ud, og så skulle han være rigtig læge. Snow, han var vokset op i York under nogle meget utroligt fattige kår. Han var den ældste af ni børn af en far, der var minearbejder. Og i sin barndom, der oplevede han meget uhyggenegnisk forhold i byen. Og det var konstant oversvømmet af spildevand. De havde også en kloakflod, der gik over sine dredder rimelig ofte. Så man havde simpelthen diareroversvømmelser inde i York, hvor John Stowe boede. Det fulgte ham faktisk op igennem livet. Ikke nødvendigvis kloakoversvømmelser, men alle mulige andre ting. Da han blev lægelærling allerede som 14-årig, der oplevede han sit første koleraudbrud. Det ramte ham så meget, at han besluttede sig for at blive noget, der hedder teetotalist, hvor man simpelthen abstinerer fra at drikke og fra at gamble og fra at gifte sig og fra at spise kød. Det abstinerede han sig fra, fordi han var blevet fuldstændig overbevist om, at usundhed og kontaminering, som han havde set så meget igennem sit liv, at det var roden til al sygdom. Så beskidt vand, beskidt mad, beskidt omgang. Det var det, der gav sygdom, og det var ikke en speciel populær tanke på det her tidspunkt her. Mærkeligt nok. Nej, du ved alt, hvad der er sjovt i livet. Især æde lort. Det er ikke godt for os. Hvad sker der lige for det? Især æde lort, ja. Som 31-årig bliver han færdiguddannet, og på det her tidspunkt er han specialiseret i anestesiologi. I 1500-tallet? Nej, det var i 1800-tallet. Okay, men stadigvæk anestesiologi i 1800-tallet. Han var en af dem, der var med til at få bedøvelse, altså fuld bedøvelse, lagt ind som en ting. Men dengang var det vel bare at gokke folk i hovedet med en hammer? Nej, det var kemisk. Hvad? Det var simpelthen medicinsk. Udfordret er en dansk videnskabskomik podcast medværterne Mark og Flemming. Hvad er den bedste måde? Så det han ligesom var specialiseret indenfor, det var narkose. Og det var faktisk at bruge det til at hjælpe fødene, så de ikke gik igennem så mange smerter, og de ikke døde så meget. Hvilket er rimelig nobelt. Og han var faktisk dronning Victorias personlige bedøvelseslæge. Eller narkoselæge. Men Snow, han er godt nok narkoselæge. Og det er godt nok et rimelig nobelt færg. Og han er også rimelig dygtig til det, og ret anerkendt indenfor det. Man kan bare ikke slippe tanken om lort. Hvad sker der? Hvad er det med det der lort og det der cholera? Hvorfor er det som om de der to ting hænger sammen? Og han var ret skeptisk over den førende teori, der var bag årsagen til infektionen. På det her tidspunkt var der nemlig to førende teorier, og den ene af dem var langt mere førende end den anden, som var basically en konspirationsteori på den tidspunkt, hvis man spurgte dem eller sølvpapir. Så den førende teori var, at cholera og andre sygdomme skyldes miasma. Og miasma, det er oversat til godt dansk, dårlig luft. Så det er grunden til, at pestlæger havde de her lange næb i deres masker og så havde roser til at sidde ude for enden. Det troede, og man kan måske tilskrive, hvorfor folk har tænkt det her. Det giver måske en rimelig god mening, fordi de gik trods alt og skidt og drak af en flod, som var bogstavelsagt opkaldt efter, at den lugtede af død. Og stinketrollen. Stinketrollen. Så måske giver det mening, at folk har tænkt, at den lugter af lort. Det kan være, at det er derfor, jeg dør. Jeg elsker, at der stinker så dårligt, at de tænker, at det er, at de dør af det stanken. Ja, præcis. Og det mente Snow ikke. Snow, han mente, at det skyldes vand. Han mente, han tilskrev i stedet for sig til det, der hed Germ Theory, som simpelthen er, at det skyldtes små mikroorganismer, som kom ind i vores krop og så begyndte at gro og gøre os syge, hvilket vi ved i dag er det rigtige. Det viste man ikke på det her tidspunkt her, og Germ Theory var ikke særlig anerkendt, og folk de syntes, at det var noget fucking rakkerprak. Hvad er det for noget pisse, du prøver at bilde mig ind? Små usynlige organismer. Hvad har du nogensinde sagt? Altså hvad? Det var da noget pisse. Men det er stadigvæk for... Det er for langt ude i forhold til skidetrollen. Ja, nu må du holde det frem. Skidetrollen, det er jo, selvfølgelig er det ham. Jeg har selv set ham. Han lugter lort, og han er brun, og han bor nede i floden. Hankies! Så hans teori, det var, at vandet i forskellige områder, det blev kontamineret med et eller andet, der overførte sygdomme mellem mennesker. Han var ikke sikker på, hvad det var, det blev kontamineret med. Men han var helt sikker på, at det var ikke bare luft. Så lang tid senere, han går med de her tankehavnkolerer i lang tid, men han arbejder egentlig med sin bedøvelse, sin narkosepraksis i virkeligheden. Så lang tid senere i 1849, der har han lavet en narkosepraksis, hvor han er ved at udvikle narkose som et rigtigt lægemøde. Og det gør han i London. Men samtidig, han har stadig kunnet slippe det her tankehavnkolerer, så han har faktisk siddet og så har han udviklet en masse matematiske modeller og prøvet at sætte årsag sammen med sammenhæng. For ligesom at vise, påvise, at der er altså en sammenhæng mellem folk, der dør og folk, der drikker beskidt vand. Og det når han lige at lave sådan et skriv, en publikation, han kan sende ud, samtidig med, at han også lige udvikler narkosekker. Selvfølgelig. Hvor han så får bevist, at koderet er skyldes vand og kontaminering af vand. Der gik jeg også en tur og pillede næse samtidig. Ja, ja, præcis. Han har jo tid til det hele. Så multitasking, ikke? Jo, jo, jo. Udfordret er en dansk videnskabskomik podcast medværterne Mark og Flemming. Jeg skulle lige til at sige det. Det er altid det der argument man hører når folk ryger. Min jeg har røget i 40 år. Jeg har det fint. Det synes jeg var på det her tidspunkt i Liverpool tror jeg det var. Der var gennemsnits levealderen. Det var 19 år. Mark og Flemming. Og så alligevel vælger man at flytte ind et sted, hvor der er lort over det hele, og gemmesensalderen er 19 år. Men det er jo fordi, det er jo ikke det American Dream, Flemming. Skal det ikke både så går, og det er sådan noget fattige bønder, de gør? Jeg skal da ind og drikke mit eget lort som en fattig bymand. Og så er det så dyrt at bo i byen, at alle de ekstra penge, du tjener på, ikke er på på landet. Dem skal du bruge på at bo i byen. Ja, og du bliver så diplomeret, at du er nødt til at drikke alle pengene op i stedet for. Jeg har nogle af de der illustrerede videnskabsblader fra 1830'erne, dem der hedder fra Københavns Universitet. Der er en af dem, hvor de har lavet en undersøgelse af selvmordsretterne i Danmark. Altså i starten af midt-1800-tallet. Og der kunne de se, at... I byen, der piker selvmord i Danmark om vinteren inde i byen. Okay. Fordi der er det mørkt, og folk bliver deprimerede. Ja. Men på landet, der piker det omkring maj måned, så den lige inden høsten går i gang. Ah! Fordi arbejdet er så hårdt. Ja. Ej, hvor sindssygt. Hvor tænker jeg, at have et arbejde, der er så hårdt, du sådan, det eneste, jeg kan gøre, det er at slappe mig selv ihjel. Det kan jeg ikke. Ja, nu har jeg drukket hele vinteren, nu skal jeg i hvert fald med goodbye. Shit, mand. Så, øhm... Han bliver håndet af hele forskningsfeltet, og de mener alle sammen, at han mangler beviser til at pakke sin poststand op. Og jeg kommer ind på den poststand lidt senere, og på, hvordan han ikke mangler beviser. Men det er fint nok. Snow er sådan, okay, cool, så går det bare lidt efter lidt beviser. Så har han arbejdet videre. Mark og Flemming. Heldigvis var ham tilgængel, og knap så heldig for London, så udbryder et af de værste tilfælde af cholera nogensinde i Soho den 31. august i 1854. Og det er lige nærheden af, hvor han selv bor. I det her udbrud her, der døde godt og vel et sted om mod 600 mennesker i løbet af 10 dage. Bare halvdelen af London dengang. Ikke helt. Snow han skriver selv, og jeg har ikke sagt det her endnu, men det her er noget jeg har taget, det er alt sammen ud fra hans egen bog. Det er sejt. Så jeg har fundet hans egen bog, som han udgav i 49, som han så ændrede på i 54 efter det her udbrud her. Så han skriver selv i den her bog her. At det kunne have, altså at den her infektion kunne have været langt, langt værre, hvis ikke at beboerne de var flygtet med det samme de opdagede af cholera på brudt ud. Så det var sådan folk de opdagede der var cholera, og så var det sådan øh fuck væk, og så døde der kun 600 mennesker. John han bliver fast besluttet på, han skal finde ud af hvad der er sket her, fordi det her, det må unægteligt kunne påvise hans påstand. Altså, han må jo simpelthen kunne bruge det her udbrud her til at finde ud af, hvad det er. Også fordi han ved, hvor det er, så han har allerede en hypotese. Så det første, han gør, det er, at han tager et kort, og så tegner han. Han krydser alle dødsfald af på det her kort her. Og så kan han ligesom lave en form for cirkel. Og i den her cirkel kan han se, lige i midten af cirklen, der ligger Broad Street Pump, som er en pumpebrønd, som er sindssygt hyppigt brugt. Mark og Flemming. Det er sjovt, at folk stadig bliver inficeret af kolera. Ham der er lortetrollen, han har vist taget til Indien i stedet for. Nej, Mark han har bare rejst. Han er udvandret. Udvandret, han må da ikke være i London længere. Nej, det vil det ikke være. Han tager ligesom et glas af det her vand her, pumper noget op og så kigger i det. Og så under, så kigger han bare på det. Og så ser han, at der er sådan nogle hvide flager, der svømmer rundt i vandet. Åh! Og han tænker, at de der hvide flager, det må simpelthen være det. Det må simpelthen være det, der gør, at folk bliver syge, fordi når han kigger på almindelig vand, så er der ikke hvide flager i. Så det må være det. Og det var der alligevel ikke. Det var der alligevel ikke i almindelig vand. Er der ikke hvide flager i vandet i København? Nej, jeg ved godt, at der er meget kalk i, men vi har trods alt ikke hvide flager. Nå. Nej, dog ikke. Jeg troede, at alle havde hvide flager i deres vand. Nej, nej, nej, nej, nej. Men han går simpelthen i gang, og han arbejder døgnet rundt. Altså hele tiden. Og han jagter information fra hospitalet. Han jagter information fra de offentlige register. Alle mulige steder for at finde ud af, om de offrer dem, der var døde, og havde de drukket af brønden. Right? Kunne han se en sammenhæng mellem dem, der var døde og hvorvidt de havde drukket brønd? Han skulle være sikker på, at alle, der var døde, eller i hvert fald så mange som muligt, at de havde drukket brønd. Han mistænkte... Fik han fandme en klavoyant, så de kunne spørge alle de afdøde? Nej, nej, nej. Det eneste han kunne gøre, det var, at han kunne tage hen til hospitalet, og så kunne han spørge dem, hvad vidste de om dem? Hvor boede de hen? Så kunne han tage ud til Folkeregistret for at se, hvor boede de i nærheden af? Hvor fik de højstens der vand fra? Og så tog han faktisk ud til folk på adresserne og spurgte de efterladte, simpelthen, hvor plejer I at få vand fra? Han var simpelthen ude på et helt, altså et detektivarbejde for at finde ud af det her. Det er nærmest ikke videnskab længere, nu er det bare rent detektivarbejde. Det er ret sejt, det er ret sejt. Men det er jo faktisk også en stor del af det epidemiologi det er. Det er at finde ud af, hvad er sammenhængende mellem hvad folk de laver og hvorfor de er blevet syge. Ja, det var også derførst, jeg var inde og se den der DayZ-film i biografen med Brad Pitt, og da jeg så, at de havde en epidemiolog med i filmen, så tænkte jeg sådan, åh, endelig er der sådan, du ved, en fed kant til den her film, som ikke er med i alle de andre zombiefilm, hvor du sådan rent faktisk får en med, der prøver at undersøge sådan sygdomsudbruddet. Og du ved, så to sekunder efter han kommer med i filmen, så falder han og skyder sig selv i hovedet. Selvfølgelig, altså han er jo sådan en forskerfilm. Ja, præcis. Han er noget kult. Ja, han er nørd. Han mistænkte ligesom, at de der boede eller arbejdede i nærheden af Brønden, de havde størst sandsynlighed for at bruge pumpen. Og på den måde også blive syge med kolera. Det giver fint nok mening for os. Det håber jeg i hvert fald. Så han opspore 100 vis tilfælde af kolera. Og ikke bare fra folk, der bor i nærheden af Brønden, men også fra skoler, fra restauranter, fra virksomheder, fra bar. Alle mulige steder går han hen og prøver at høre, har I ikke drukket af Brønden? Er I døde? Alle steder, han kan komme til. Så han skriver i bogen, at Arjan er en kaffebar, der ligger lige ved siden af. Hun serverer Broad Street vand med sine måltider. Og hun havde oplevet, at ni af sine kunder, de havde fået cholera. Men han kiggede ikke kun efter personer, der havde fået cholera, fordi han var ligesom nødt til at prøve at modbevise sin hypotese. Så han kiggede også efter personer, der ikke havde fået cholera, men som stadig boede i nærheden af Brønden. Hvorfor havde de ikke fået cholera? Det er vigtigt, fordi han er nødt til at udelukke, at folk kunne drikke af vandet uden at blive syre. Fordi i stort tilfælde, så var det ikke sikkert, at det var vandet. Så kunne det jo være alt muligt andet. Så kunne det jo være lugtetrollen i stedet for. Så i et fængsel i nærheden af Soho, der havde de 535 indsatte. Men stort set ingen kolerertilfælde. Og Snow opdager, at fængslet ikke får vand fra den her brønd her. De køber deres vand fra et vandværk uden for Soho. Så de får vand fra et andet sted. Okay, cool nok. Så er der et bryggeri på Broad Street, lige ved siden af Brønden nærmest, hvor de laver whisky. Og her var der ingen arbejdere, der havde fået koler. Det er ret mærkeligt, fordi de bor ret tæt på pumpen. Men ejeren fortæller, at arbejdere enten drikker det whisky, de laver, eller så drikker de vand fra bryggeriets eget brønd. Så bryggeriet her har simpelthen en egen brønd. Hvis du får muligheden for ad libitum-viski, så drikker du ikke vand. På det her tidspunkt, der er sprit meget renere end vand. Det er jo også derfor, man brygger meget øl. Der var en dansk konge i 1700-tallet, der anbefalede børn at drikke en masse øl hver eneste dag. Der er masser af næringøl. Jamen, du får også... Jeg tror, at mange af de mikroorganismer, der bruges i bryggeriprocessen, de udkonkurrerer de sygdomsomkaldende. Men du koger også på opløsning, inden det er, at du... Udfordret er en dansk videnskabskomik podcast medværterne Mark og Flemming. Udfordret er en dansk videnskabskomik podcast medværterne Mark og Flemming. Og den fabrik sørgede altid for at have to baljer med Broad Street vand til alle hele tiden. Det var ikke alle tilfælde, hvor det var lige nemt at lægge to og to sammen for snow. Så der var et problem med en niæse og en tante, der var død af cholera, men hvor tanten hun boede sygt langt væk fra Soho. Det gav ikke rigtig mening, hvorfor skulle hun få vand fra brønden der. Altså der var masser af brønden i nærheden af hende i stedet for. Og der var virkelig langt til Soho for at hente det. Så det var faktisk først, da Snow han fik fat i tantens søn, at sønnen kunne fortælle, at tanten engang havde boet på Broad Street. Og hun havde åbenbart kunne lide vandet så godt, at hun simpelthen havde fået sin njæse til at komme med et par flasker til hende regelmæssigt. Og den 31. august, den dag, da kolera var brudt ud fra brønden, der havde njæsen netop været nede og hente vand ved brønden. Og så var hun gået tilbage til tanten, og traditionen tro, så da hun var kommet dertil, så tog de lige et glas og forfriske sig på. Og så døde de selvfølgelig af kolera begge to. Årh, det er fandme uheldigt, det der. Sygt uheldigt, men virkelig, virkelig vigtigt for Snow. Fordi han bliver ved med at kunne se, at koleratilfælde rører tilbage til pumpen, og folk, der ikke har kolera, de drikker vand af noget andet i stedet for. Så den 7. september, en uge efter udbrudtsstart, der tager Snow alle sit data her. Og så tager han det med hen til byens embedsmand. Og så prøver han at overbevise dem om, at de er nødt til at fjerne håndtaget til pumpen. Og de her mænd i højhattet, de kigger lidt på Snow, og så siger de, hvad skal folk så drikke af? Men der er jo ikke så mange mennesker i det område alligevel, fordi de er alle sammen flygtet. Så okay, lad os prøve at gøre det på prøve. Hvad kan der ske? Altså, der er ikke nogen derud alligevel. Så Snow, han får et par politimænd med hen, og så tager de håndtaget af pumpen. Og så stopper udbruddet. Basically med det samme. Der er basically ikke flere kolerat tilfælde, efter de får fjernet håndtaget. Nærmest med magi. Men selvom Snow virkede til at have ret, og selvom hans hypotese her var succesfuld i at stoppe choleraudbruddet, så var der ingen, der troede på ham. Selvfølgelig var der ikke det. Nej, pumpen. Det var et tilfælde. Det er ikke derfor. Han skulle have haft en klaveriant med i stedet for, så havde de troet på ham. Ja, ja. Ja, ja. Det var fordi, at jeg talte med lugtetrollen, når han sagde, at han var gået væk fra Brønden, efter de havde taget håndtaget af, så gad han ikke være dernede. Jeg kunne mærke ham. Det var fordi, han var blevet sur over, at det der håndtaget larmede, når han lå og sov til middagslure. Kan også bare have givet skylden til Maren nede fra nummer 9 og sagt, at hun var heks. Var det ikke slemt i 1800-tallet? Det ved jeg ikke, det var det nok ikke. Nej, jeg ved det faktisk ikke. Hvem ved? Jeg tror ikke, man havde hekset ind i byen, Flemming. Det måtte man nok ikke. Så var man ikke sej. Så der var ingen, der troede på ham. Det var ren nonsens, det han snakkede om. Og embedsmændene, de nægtede at rengøre eller lukke affaldsbrønden, og de nægtede at lukke eller rengøre kloakker. Det var jo snods i hele hans idé. Det var jo, at der var en kontaminering. Altså, vandet var jo ikke forurenet af sig selv nødvendigvis. Det var jo nok fordi, at der kom cholera ind fra en eller anden anden sted, hvor det var forurenet. Så bestyrelsen udsendte en rapport, hvor I skriver, at vi ser ingen grund til at antage denne tro. Og i stedet kaldte de Snows opdagelser for forslag. Det var, hvad det var. Det er fuldstændig ligesom forskning i dag. Ja, fuldstændig. Så i månedsvis efter, der arbejder Snow på at opspore samtlige cholera tilfælde fra det her udbrud her. Og han fik forbundet næsten alle tilfælde tilbage til pumpen. Næsten alle 600 tilfælde. Okay. Inklusiv en skabsmager, der bare lige var gået forbi oprådet. Han boede der ikke, han var der ingen steder. Han var bare lige gået forbi, og så havde han lige taget et glas vand, mens han var gået forbi, og så var han død af det. Mark og Flemming. Mark og Flemming. Dansk videnskabskomik podcast medværterne Mark og Flemming. Og det han faktisk gjorde som præst, hvilket jeg synes er rimelig sindssygt, det var, at han arbejdede med at falsificere falske hypoteser. Det var simpelthen, at når han så en forsker, der satte hypoteser op, så var han sådan, okay, så tester vi dem. Så kan vi ud og se, om de er rigtige eller ej. Okay, det er ret sejt. Jeg skulle lige sige, at fuck han er nederen, men det er meget badass. Præcis. Altså, at han så tænkte, at det hele var Guds guddomlige indgreb, det er jo så hvad det var. Men han arbejder ligesom for at, han sætter sig for at modbevise Snow. I sit forsøg på det, der bliver han faktisk så overbevist af Snow, at han skifter mening. Han tror på Snow. Han har sådan et, det er ikke Gud det her, det er vand, det er 100% vand. Har du set, at hans data, altså sin matematik, bror, det er 100% vand, det kommer lige dernede fra. Jeg kan se det. Sikkert bare en af de der hvide flager, der har lignet en lille engel eller sådan noget. Gud har nok bare puttet de hvide flager ned i vandet. Så præsten går faktisk i gang med at interviewe beboerne, der ejer en adhænder Brønden. Så man går rundt og spørger folk, hvad ved I om det her? Hvad tror I, der er sket? Og så kommer han i snak med en kvinde, der bor lige ved siden af Brønden. Og hendes børn havde begge to fået kolera, men fra en anden kilde. Og det ene af de her børn her, det var et spædbarn. Og det var jo rimelig synd, fordi børnene var jo døde af det. Det er jo... Det er jo ærgerligt, men om ikke andet, Flemming, du ved, du kender efterhånden alt til børn med diaræ. Ja. Og I bruger ikke stofblære, det går jeg ikke ud fra. Altså, vi bruger stofblære til at tage ting op med. Okay. Og så får de almindelige blære på. Ja. På det tidspunkt var der jo ikke almindelige blære, der var en stofblære og en almindelig blære. Åh, nej Mark. Og Flemming, når man ikke er civiliseret nok til at have udviklet engangstblære, så skal stofblære altså vaskes en gang imellem. Udfordret er en dansk videnskabskomik podcast medværterne Mark og Flemming. Og fuck, i det mindste, jeg troede lige hun havde smidt det døde spædebarn ned i brønden. Ej, okay, dog ikke. Så kan det være trolden han bliver glad, så får han et offer her. Ej, måske. Og den her afføringsbrønd, hendes afføringsbrønd, den var selvfølgelig læk. Det er jo klart, selvfølgelig var den læk. Det er jo præsten, han har jo faktisk fundet ud af, hvor det kommer fra nu. Men hans opdagelser, de bliver først publiceret et år senere. I et eller andet bestemt tidsskrift. Og det her tidsskrift, de publicerer det med en bøn om at opdatere kloakeringen i London. De siger simpelthen til Londons embedsmænd, Please for fuck's sake, gør noget ved de her kloaker her. Folk de dør af cholera, fordi de vasker deres stofblære og kaster vandet ud i afføringsbrønden. De må have gjort noget. Hvad tror du, Londons embedsmænd siger til det? Jeg tror de siger, jeg hører hvad du siger. Men nej, det bliver for dyrt. Ja, det var noget fjollet noget. Hvorfor? Men det er jo ikke vand, det er jo dårlig luft. Ved du, hvad du siger til mig? Det er jo ikke noget med vand, det er jo noget pjat. Jeg elsker, at idéen om, at dårlig luft er så nem at tro på i forhold til dårlig vand. Altså, what the fuck? Det er først mange, mange års, eller ikke mange år senere, jeg tror det var fem år senere eller sådan noget. Der havde de været igennem en periode, hvor de havde kaldt for The Great Stink. Hvor at temsten havde lugtet så dårligt, at folk ligesom havde navngivet det her periode af tiden, efter hvor dårligt floden den lugtede. Jeg har godt læst om, at der også lå lig og fløde rundt i den og sådan noget. Jamen alle mulige sindssyge ting, ikke? Så på det tidspunkt, der var der så en civilingeniør, der hed Joseph Balgazet, som satte sig for simpelthen at opdatere hele Londons kloaksystem. Og hans klorokeringsarbejde, det er faktisk stadig brug i den i dag, i det 21. århundrede. Det er ret badass. Efter at de er gået fra at være måske en halv million op til at være otte millioner i stedet for. Men kan det godt holde til otte millioner mennesker nu så? Ja, så det de har gjort, det er at de har ligesom let hans originale klorokering ud og sat det fast til rensningsanlæg i stedet for. Men rørene i sig selv og infrastrukturen er der ikke noget problem i. Jeg tror, at de har opdateret rører, der ligesom er tærede eller sådan noget, men ellers så er infrastrukturen perfekt. Jeg mener bare, at jeg har hørt om for nylig, at der er problemer med det originelle kloaksystem nu, fordi det kunne ikke opretholde lorteproduktionen for så mange mennesker, men at det i sig selv var så godt struktureret, at det egentlig stadigvæk fungerede. Det kan være, at mit er en lille smule outdated, det skal jeg ikke kunne sige. Men det er også bare, jeg elsker logikken, det er ikke vand, der har rørt lorten, der er problemet. Det er luft, der har rørt lorten. Så derfor skal vi jo ikke fjerne lorten. Det går lige meget om, du tror det er vand eller luft. Hvis lorten gør luften dårlig, så får lorten væk alligevel. Det er ikke lorten. Det er løsningen på det samme. Det er ikke lorten. Det må ikke være lorten, Flemming. Fordi hvis det er lorten, så bliver man jo syg af, at man får lort ind i kroppen. Så de tror ikke på, at det er lorten, der gør luften dårlig? Ah, fordi Flemming, jeg får ikke lort ind i kroppen. Ej, det er sikkert bare sådan nogle, min lort, den lugter godt. Jeg kan godt lide lugten af min egen lort. Min lort? Det kan ikke være det. Ej, min lort, den er, den er, det er en god lort, det har jeg jo fortalt dig. Det må være et nyt spørgsmål på et tidspunkt. Hvorfor er det kun ens egen lort, der lugter godt? Ens egen lort lugter ikke godt. Okay, hvorfor er det kun min lort, der lugter godt? Flemming, din lort lugter heller ikke godt. Sorry to say. Jamen, jeg må lige send Jon Snow får ligesom påvist, at det er kolera, der kommer fra den her pumpe her, og at der er en dame, der har vasket sin kolera-babystofblæ og kastet badevandet ned i brønden, og det er derfor, folk får kolera. Men det arbejde er han faktisk ikke specielt stolt af. Han har faktisk gemt det en lille smule i sin bog, fordi han er ikke så interesseret i det her, fordi han ser det ikke som særligt videnskabeligt, fordi det er det jo i virkeligheden heller ikke. Det er jo detektivarbejde, men det er jo ikke så meget videnskab. Og i mange år i forvejen, der har han været i gang med matematisk at definere årsagen til cholera. Og det tænkte han jo, det ville være robust evidens. Altså mere end den der anekdotiske evidens, han havde fra den her pumpesituation. Så jeg ved ikke om du kan huske, at jeg sagde, at han havde udgivet en bog, en publikation i 1849 allerede. Øh jo, hvad var det nu om? Jamen det var faktisk fordi han havde opdaget at sammenhæng eller sammenlægning af to vandværker i London havde fået dem til at flytte deres pumpe lokation. Sådan at de her to vandværker der var blevet til et vandværk nu, de var begyndt at pumpe længere nede fra Temsten end de har gjort tidligere. Åh nej. Og hvis du pumper længere nede fra Temsten så får du også mere lort med. Så er det tættere på trolden. Det sidder tættere på trolden. På et tidspunkt var der en læge, der hed Dr. Hassal, som heller ikke troede på Jon Snow, men det kan Jon selvfølgelig være ligeglad med. Han undersøgte vandet fra de her virksomheder, og han fandt som det mildeste dyrehår i vandet, man fik fra de her vandværker. Og det var ikke noget problem? Nej, jeg sagde det mildeste. Andre steder kunne man nok finde hvide flager, og andre steder var vandet nok ikke helt så gennemsigtigt, som det burde være. Da ingen troede på, at vand var skyldig sygdom, så var der heller ingen, der så den her sammenhæng mellem forskellige vandværker og andelende sygdom. Det er jo lige meget, hvor jeg får vand fra. Jeg ved ikke, hvor jeg får vand fra. Jeg bliver syg alligevel. Alle bliver syg. Det er jo lige meget. Jeg kan ikke se det. Så snows egentlig innovation lå ikke i at interviewe folk, selvom det er sådan, historien bliver fortalt. Hans innovation lå i matematisk at opdele folk geografisk, baseret på dødsretten i området, og så derefter at finde sammenhæng. Men hans hypotese, altså at kontamineret vand skulle være skyld i sygdom, blev udsat på en perfekte test. Fordi han havde det ene, det samlagte vandværk, som havde lortevand. Og så var der faktisk et andet vandværk i London, som gav filtreret vand i stedet for. De tog simpelthen vand længere oppe af Thimsen, hvor der var mindre spildevadsudledning, og så filtrerede de det, så man ikke fik partikler med, og så gav de det videre til folk bagefter. Og det var ret perfekt, fordi uden at vide det, så var hele London blevet delt op i to lejre. Der var den lejre, der fik lortevand, og der var den lejre, der fik almindelig vand, rent vand. Og det vidste de ikke, men han skriver selv sådan, at det er alle mennesker, der er blevet delt op. Det er sådan, om du er rig eller fattig, om du er den ene eller den anden rase, om du er høj eller tynd eller whatever. Det er ligegyldigt, hvad du er, fordi folk de ved ikke, hvilken vand de får. Så de har bare, altså det er fuldstændig spredt, hvad folk de har fået vand. Men de har enten fået det ene eller det andet. Så det første, han ligesom opdager, det er, at han kan skælne mellem de her to typer vand. Han kan simpelthen, uden bare at kigge på det, fordi det er måske ikke så videnskabeligt i sig selv, men han kan simpelthen skælne ved med en kemisk test, fordi han har opdaget, at der er mere salt i det urene vand, end der er i det rene vand. Muligvis fordi folk har skivet kolera, hvad hedder det, mausesaft ud i det urene vand, og derfor er der meget salt i. Det er svært at sige. Årh, det er røvsalt. Røvsalt, muligvis. Så han har simpelthen lavet en test, hvor han kunne undersøge, hvor meget natriumklorid det var i. Det gjorde han ved at komme noget sølvklorid i, tror jeg, eller sølvjoner i, fordi så binder disse kloriden, eller s Og så kunne han bare måle, hvor mange sølvkorn der var i. Og så kunne han se, at der var 90 gange så meget salt i det konsumerede vand, som i det rene vand. Så det var rimelig godt til videre. På den måde, så kunne han gå fra hjem, i stedet for at gå fra hjem til hjem, fordi folk de anede ikke, hvilken vand de havde, så hvis jeg spurgte dem, hvorfor er jeres vand fra, så kiggede de på mig sådan sådan, vand? Det drikker jeg da. Det får da fra brønden. Det kommer jo ned fra jorden eller op fra himlen. Ja, det kommer da. Jeg tror, det er bare det, der er. Det kommer nok ud fra havet på et eller andet tidspunkt. Så i stedet for det, så kunne han simpelthen gå fra brønd til brønd og fra hjem til hjem, hvorinde de havde vand. Og så kunne han spørge efter en lille prøve, og så kunne han bare måle, hvor meget salt der var i, og så kunne han krydse af. Du får kontaminerede vand, du får rent vand. Og på den måde, så er ikke mindre end 300.000 mennesker af begge køn, enhver alder, alle rang og stand, rige og fattige, de er blevet delt ind i to grupper, uden at vide det. Så en gruppe, der blev forsynet med vand fra Lottes Kloak, og blandt andet det, der måtte komme fra koldeapportienter, og en anden gruppe, der ligesom var fri for de her urenheder. De er adskilt af tarmsaftens kraft. De er adskilt af tarmsaftens kraft. Den er ligeglad med rase, alder og køn. Det er tarmsaftens kraft af den ultimative unbiased force of nature. Tarmsaftens kraft, vi kan ikke måle os med, hvor stærk den er. Lad dig kue af tarmsaften. Pas på, tarmsaften kommer. Det er jo ret cool, fordi når han kan dele de to grupper op, så er der ikke så meget, der gør, end at tælle, hvor mange er døde i den ene gruppe, hvor mange er døde i den anden gruppe. Og så kigge på, korrelerer det. Er der en sammenhæng mellem, hvilket vand, man får, og om man dør af kol eller hvad? Og Flemming, det passer jo, altså, det kunne ikke korrelere bedre, fordi selvfølgelig dør du, når du drikker kolder og vand. Det er jo klart. Så det var jo nærmest en ær i anden værdi på en. Altså, det var jo en lige korrelation. Det var jo den perfekte sammenhæng, der var. Men det er jo ret ligegyldigt inden for videnskab, hvis ikke du også har en årsag. Mark og Flemming er en dansk videnskabskomik podcast medværterne Mark og Flemming er en dansk videnskabskomik podcast medværterne Mark og Flemming er en dansk videnskabskomik podcast medværterne Mark og Flemming er en dansk videnskabskomik podcast medværterne Må jeg gætte på, at embedsmændene i byen, de vil ikke gå med til det, fordi det vil være for dyrt. Så i stedet for så de kontaminerede pumper, dem maler de bare røde, og så brander de det som Coca-Cola, for at få folk til at drikke det med glæde. Er det det, vi dør af, når vi drikker Cola-Flemming? Coca-Cola-Rare. Cola-Cola-Rare. Det er 1800-tallets smag. Det var en sponsor, vi tabte lige der. Det ved jeg ikke. Jeg tror ikke, de har lyst til at sponsorere os efter det afsnit, vi lavede. Nej, nu har de slet ikke lyst til det. Tænk over farven. Den er også rimelig sortbrun. Jamen, det er rigtigt. Ligesom troldens... Jamen, jeg tror, der er en koalition her. Hvorfor tror du, det bubbler? Hvad er brusen? Jeg tænker simpelthen, det er kolerabakterierne, der trækker vejret. Altså, at bruges i fermenterede produkter er jo faktisk skabakter, der lader CO2. Det er prutter. Det er prutter. Det er mikroorganismerprutter. Det er meget poetisk. Det er det. Så det kunne godt være kolera-prutter. Ja. Coca-Cola-ra-prutter. Coca-Cola-ra. Vi trademarker det. Det tror jeg ikke, det må. Det tror jeg er en rigtig dårlig idé. Det tror jeg virkelig, virkelig dårlig idé, Flemming. Det tror jeg overhovedet ikke skal gøres. Kan du ikke photoshoppe sådan en flaske til mig, Mark, med diarætvand i? Jeg har ikke lyst. Jeg skal ikke have, at det bliver lækket. Det har jeg ikke lyst til. Nå, det vil jeg ikke. Jeg skal ikke have, at Coca-Cola banker på min dør. For jeg ved det. Hvad er det her? Er det en flaske med kloakvand? Jeg ved, at de waterboarder mig med Coca-Cola, og jeg vil ikke have det. Åh ja. Jeg har faktisk hørt, at der var en, der fortalte mig på et tidspunkt, at en torturmetode, man bruger med waterborder folk i virkeligheden, altså militæret og sådan noget, det er faktisk, at man viser dem Coca-Cola-logoet, mens man waterborder dem. For at de bliver tørstige? Nej, fordi Coca-Cola-logoet, det er det mest genkendelige. Mark og Flemming. Det er et godt spørgsmål, bare for at være ekstra nederen måske. Fuck dig, og os som 10 år. Ja. Hav det rigtig dårligt hele dit liv. Ej, hvor er jeg glad for, at jeg endelig fik en mulighed for at bruge min Coca-Cola-waterboarding-anekdote. Det har du ventet på i mange år. Jamen, det var lige lejligheden bød, så Mark. Okay, fanden. Så han får påvist sin hypotese matematisk. Det korrelerer, at hvis du drikker numsejuice, så får du kolera, og hvis ikke du drikker numsejuice, så får du ikke kolera. Og han får den også testet i fængslerne, hvor han ser, at hvis fængslerne holder op med at servere numsejuice, så får folk ikke kolera. Det er som om, at der er både en årsag og en sammenhæng her, Flemming. Men som du har hørt allerede en tredjedel inden i mit afsnit, så var det ikke nok for de høje her i London. Selvom han havde både statistisk evidens og praktisk evidens, og nu efter at han så også havde praktisk evidens fra pumperne, så var folk stadig sådan, det er vi sgu egentlig ret ligeglade med. Men det han lærte af det her, det var ret vigtigt, og det er faktisk det, der ligesom er epidemiologi i dag. Det er nemlig, at statistisk evidens skal kombineres med videnskabelige observationer for at kunne overbevise folk. Så hans statistiske evidens, som han tænkte, var det mest robuste data, han havde, det robuste bevisbateriel, han havde, det var ikke nok. Folk var ligeglade. De har sådan en statistik, og hvad så? Det er fuldstændig ligesom det, vi snakkede om sidst med chimpanzerne. Ja. At folk var ligeglade med at høre om adfærdsbiologien. De ville høre historier om aber. Det er præcis det samme, ja. Fordi da han så kom med den her pumpe, i stedet for at han kunne sige, det er blæn, så var folk sådan, det er blæn. Og det er det, der simpelthen har sat præcedens for moderne epidemiologi, som vi kender i dag. John Snow, han nåede aldrig at finde ud af, hvad de der hvide flæger i hans vandprøve det var. Men han spekulerede selv i, at det måtte have noget at gøre med de der nye animalcules, animakugler, som vi har snakket om tidligere. Ej, hvorfor kalder man ikke det mere? Det burde man. De der, som der er blevet snakket så meget om, er de der moderne hollandske mikroskopister. Vi kunne jo godt begynde at kalde det dyrekugler, i stedet for bakterier. Men det er jo dyrekyler. Dyrekyler, nå ja. Ja, dyrekyler. Mark og Flemming er en dansk videnskabskomik podcast medværende. Mark og Flemming er en dansk videnskabskomik podcast medværterne Mark og Flemming. Det er det. Han nåede aldrig nogensinde at opdage, at cholera skyldes en bakterie, som simpelthen blev isoleret. Det er tragisk. Det mest tragiske, Flemming, det er, at cholera bakterien allerede blev opdaget af en italiensk forsker i 1854. Så det år, da udbruddet blev opdaget i London, der var der en italiener, der havde opdaget cholera bakterien, at det var en bakterie. Nå, ja. Og det ville jo have været virkelig brugbart for Snow. Men det var først efter ham da italienernes død, at han blev krediteret for overhovedet at have isoleret den. Så han isolerede den jo, hvad, 14 år før, hvad havde du, nej, 29 år før Robert Koch. Men han blev jo ikke tilskrevet noget kreditering for det. Så kunne han bare lade være med at være italiener jo. Jamen det var jo det. Og det var faktisk fordi han var italiener, fordi i Italien der troede alle italieniske forskere på miasma, altså dårlig luft, i stedet for germ theory. Hvad hed han sagde du? Han hed, øj det har jeg ikke engang skrevet ned. Ej, det er virkelig dårlig stil. Det er nok bare fordi, hans navn ikke har været særlig godt. Han hedder Patini, er jeg ret sikker på. Ja, prøv at høre. Patinis postulat, det lyder ikke særlig sejt. Åh, det lyder faktisk virkelig sejt. Cox postulat er meget nemmere at sige. Der er ikke nogen, der kan stave til det andet. Prøv at høre. Patinis postulat lyder virkelig cool. Det skulle da have heddet. Det vil jeg virkelig gerne. Det kan du jo ikke stave til. Det er ligesom Fibonacci-tallet. Altså, fuck nu af. Det er da mega nemt at stave. Nej, det lyder også. Kunne du ikke Og det endnu vildere er faktisk, at ham i Italienerne udgav fem publikationer yderligere, der detaljeret beskrev sygdomsforløbet årsagerne og endda foreslog behandlinger. Men fordi at folk i Italien var ligeglade med ham, så var det bare jævligt. Sådan. Ja. Og den blev faktisk også opdaget af en katalaner, altså en gut fra Barcelona i samme år i 1854. Det kunne snå virkelig godt af ham. Og så kom Robert Koch bare der. Haps! Ja, præcis. Han er allerede kendt for, jeg kan ikke forstå, Basilus eller hvad det var. Det var historien om Jon Snow og Broad Street-pumpen og hans grundlæggelse af moderne epidemiologi. Flemming, jeg tror aldrig nogensinde, vi har været så godt på tid som i dag. Var det ikke lige præcis? Nej, det er rigtigt. Den er faktisk lige præcis om 16 sekunder, Mark. Nå, min den siger 10 nu. Min siger 9,5. Okay, det gør den faktisk godt, fordi jeg sidder og kigger på pilen. Ja, okay, okay, okay. Det var faktisk ret imponerende, Mark. Lige præcis intimt. Jeg har gjort. Jeg har gjort meget for at finde ud af det. Jeg tror ikke engang, jeg har sagt særlig mange stødende jokes ved noget til at klippe ud. Nej, nej, nej. Det er super. Det er et ret sejt stykke arbejde, han har lavet. Jeg er egentlig ikke særlig forarvet over, at de ikke troede på ham, fordi jeg virkelig sådan en menneskelig dumhed har, kender mig ingen grænser. Altså, det er... Altså, men det er... Hvide flager i ens vand. Altså, jeg tror... Den person, altså hvis der er nogen, der skal blive rigere end Jeff Bezos og Elon Musk i det 21. århundrede, så tror jeg, at de skal finde en måde, hvorpå vi kan komme til at drikke afføringsvand igen uden at få cholera. Kan man ikke bare... Ja, men du... Fordi det er jo et kæmpe marked, vi har her, som ikke er blevet taget ind i. Altså afføringsvand. Det må jo være fantastisk, fordi alle drak det i 1800-tallet. Afføringsvand. Du må ikke kalde det afføringsvand. Og de var jo tydeligvis meget imod Og stop med at drikke afføringsvand, eller risikere døden, inden de vil stoppe med at drikke afføringsvand. Så vi må have et eller andet, altså, hvis vi kan finde ud af at bevare, du ved, hårene og skorpen på vandet, og farven og smagen, men så fjerne al koleraren, så tror jeg altså, at du kan blive virkelig, virkelig rig. Men kan man ikke bare pasteurisere det, tror du? Tror du ikke, at man bibeholder lortens gavnlige egenskaber, og bare fjerner alle de dårlige egenskaber ved at pasteurisere dem? Dansk videnskabeligt Udfordret er en dansk videnskabskomik podcast medværterne Mark og Flemming. Og så i stedet for at pasteurisere det, så lad det stå ved 30 grader i et par dage. Og så giv det til folk. Og så centrifugerer det ligesom mælk, ikke? Du har mini Coca-Cola og let Coca-Cola og så helt ude til fløden. Fløden er der, hvor al den gode afføring er og alle hårene og skorpen. Hvad blander du tilbage i afføringsvandet for at få de der tre faser? Normalt centrifugerer du mælken og så blander du vand. Er det vand, du blander i? For at få tyndt det? Det tror jeg ikke. Jeg tror bare, at du skiller mælken ad. Nej, men der er ikke tre faser, er der det? Du tager bare råmælken, og så centrifugerer du den under forskellige forhold, tror jeg. Er du sikker på det? Tror jeg. Jeg aner det ikke. Det er det, jeg har fået at vide i gymnasiet. Nå, det er jo bare forskellige fedtindhold, du har i de forskellige typer mælk. Tror du ikke bare, at det kommer an på, hvor længe og hvor hårdt man har spundet det? Du kan så bare fjerne det af flere omgange. Det kommer an på, om du kan spænde fedt ned. Kan jeg vide, hvad afføringsvandsudgaverne kernemilk er? Er det det, alle majskærnerne er i? Kernemilk er jo det, du ligesom har. Det er jo, når du har kernet smør. Så det er, hvis du har stået og masseret lorten længe nok. Så er det, der kommer ud af det. Og så når du har lavet ost på den, så har du valden tilbage. Ja, og valden har majskærner i. Ja, okay. Den er jeg med på. Og hvis du bløder det op med vand, og så kommer syre i, og så har du lavet det stå et par dage, så er det hytteost, men er lort. Er det ikke et rigtig godt afsnit, det her? Nikolaj, du bliver nødt til at klippe det her ud, for vi vil ikke have nogen, der stjæler den her forretningsmodel. Vi spilder vores evner på at lave den her podcast, Mark. Vi skulle bare have startet virksomheder op i stedet for. Jeg vil gerne se, hvor hurtigt en virksomhed, der starter op med konceptet lort, hvor hurtigt den lukker ned igen. Hvis nogen kunne gøre det, så var det os. Lort, du kan drikke. Bill Gates vil sikkert investere i det. Tror du det? Han er jo vildt interesseret i, hvad vi kan stille op med alt det lort, der er. Det er rigtigt, det er rigtigt. Han har jo brugt flere millioner dollar også på at foreskrive, hvordan man kan lave lort om til brændstof. Kan du huske det? Jo, jo, jo. Hvad er problemet? Vi drikker altså sgu da bare. Og det er det, han vil gerne, altså hans tre mærkesager, det er lort, og det er sult, og det er børnesygdom. Så du ved, man kan faktisk kombinere den her. Tre i én? Du kan fjerne lorten ved at lave den om til mad, og ende sulten, og så fjerne koleraden til børn, altså som en af de værste børnesygdom. Ja, ja, ja, ja, ja, ja. Og han er jo lige blevet skilt, så han mangler sikkert et eller andet at fokusere på, så jeg tror lige, vi skal prøve at ringe til ham. Det er en god idé. Har du hans nummer? Dansk videnskabeligt Udfordret er en dansk videnskabskomik podcast medværterne Mark og Flemming. Dansk videnskabskomik podcast medværterne Mark og Flemming. Vi har vores fangruppe, moderatorgruppe. Det må være dem, der skal kontaktes. Ja, det er i hånden. Tag lige og kontakt dem, Bill Gates. Vi dokser lige Thijs og Felix. Billy Boy. Så kan I se. All right. Cool. Tak for det, Mark. Velbekomme. Jeg... Det var virkelig ulækkert, men ikke på den dårlige måde. Det var ikke sådan, at jeg sad og var ved at dø, jeg hørte på det. Jeg synes, det er meget fascinerende, når det er lort. Så det er faktisk... Det første gang, jeg var formodet at lave et afsnit, var ikke at skræde, tror jeg. Hold da op. Jeg er glad for, at der ikke har været en eneste afskåret penis i hele det afsnit, og det sætter jeg virkelig pris på. Ej, det var fandme en fejl. Ja, nej det var det ikke. Altså jeg er glad for, at den her udvikling især i podcasten, at den bliver mere professionel nu. Ej, det har jeg virkelig ringet mig. Det er jeg faktisk virkelig ked af, Flemming. Undskyld, kære lytter, at Flemming ikke havde det dårligt i dag. Jeg er glad for, at vi kan appellere til en bredere lytterskare nu, hvor Mark ikke snakker om afklippet peniser, men i stedet for at snakke om folk, der drikker lort. Hvorfor hører folk det her? Hvorfor er der nogen, der gider at høre det her? Jeg forstår det ikke. Skulle vi ikke lave en virksomhed, hvor man skal drikke sin lort? Jo, det var en mega god idé. Hvis I kender nogen derude, eller hvis I hører det her, når I hører det her, så skriv lige til os, hvorfor I hører det. Der er ingen, der hører det. Så ved det jo, der er ingen, der gider at høre det her. De har jo slukket for 50 minutter siden. Nej, Mark. Jeg tror, det er din mor, der hører det rigtig mange gange. Ikke når vi stræler med at drikke af. Altså jeg vil gerne, jeg vil høre, altså hvis jeg kunne finde en podcast, der handler om folk, der snakker om lort i halvanden time, så ville jeg ikke høre andet. Nej, men det ved jeg godt, Flemming. Du er også bare virkelig, virkelig en niche-målgruppe. Tydeligvis ikke. Der er jo mange Flemminger derude. Det kan jeg godt fornemme. Ja, okay. Du har måske ret. Det er rigtigt. Mark Gargablark. Tak for det. Skal vi tage nogle lytterspørgsmål? Nu er vi jo i god tid i dag. Det er en god idé. Det synes jeg. Har vi nogle lytterspørgsmål? Ja, ja, ja, ja, ja. Åh, yes. Det gode begyndelsespørgsmål er, at når man har læst dem op, så kigger Flemming først ud til højre, så kigger han ud til venstre, så får han en blik, hvor han virkelig får fuger ved øjenbrynet, og så kigger han skråt op, som om han tænker. Og så læner han sig bagud, så tager han armlårets kors, så lægger han sig bagud, så han er så langt væk fra mikrofonen som overhovedet muligt, og så skal man sidde, så skal man underholde, mens Flemming tænker over hans svar. Jeg sidder lige og tænker, Mark, herovre. Jamen, det ved jeg, du gør. Under... Og det er virkelig godt. Hvorfor er de blevet designet? Det må jo fordi, de må udfylde en evolutionær nische. En nische, som hedder at flyve. Men jeg tænker måske, så du ved, der er jo evolutionære nischer til alting. Der er bakterier, der lever i konevand på bunden af havet. Udfordret er en dansk videnskabskomik podcast medværterne Mark og Flemming. Jeg tænker, hvad er den evolution of Indonesia? Det må næsten være fordi, at de har en livshistorie, det er det, man kalder det på dansk. Hvordan er deres livscyklus? Og det må ligesom være en vigtig fase i den her livscyklus, at de flyver ind i øjnene og munden på os. Så der er jo nogle forskellige muligheder. Så den ene mulighed det er, at det er de gamle dyr, som simpelthen skal fjernes fra populationen, så de ikke, altså hvis de ikke længere er frugtbare, så de ikke fjerner værdifulde ressourcer fra de dyr, der stadig kan formere sig. Så det kunne ligesom være en mulighed for dem, at de simpelthen bare går selvmord ved at flyve ind i øjnene på os. Men jeg tænker en mere interessant idé, det er sikkert, at det er fordi... At vi bare er et led i deres livscyklus. Jeg forstod meget lidt af det der, jeg tror ikke på det. Jeg tror, at de flyver ind i øjnene på os, så de kan lægge æg under vores øjnelov. Uh, det kan jeg godt lide. Det synes jeg er en god idé. Jeg tror, det er fordi, at de er så fulde, at de falder i søvn midt på vejen, mens de flyver. Og så når vi kører ind i dem. Det er faktisk også det køn i Danmark, dem er førende også. Men de når lige at vente sammen og sige sådan... Jeg elsker din idé om, at hvis man falder i søvn, mens man flyver, så hænger man i luften der, hvor man falder i søvn. Hvis en flyvemaskine går i stykker og går i stå, mens du flyver, så hænger den bare og svæver op i luften. Det gør den da. Nu skal du ikke komme her og spille smart. Jeg sagde jo, at det er fordi, at når man er fuld, og man falder i søvn, så bliver man ved med at gøre det, som man gjorde, inden man falder i søvn. Nu har jeg set dig falde i søvn, du fulde mig. Og jeg går tit rundt. Du går, det er rigtigt, altså du går bare lige ud ind i væggen, mens du sover. Der kan du se, det er jo det samme, de har gjort. De er bare sådan, de falder i søvn midt hvor de er, og så står de bare sådan. De hænger bare i luften, Flemming. Som en helikopter. Og så når de lige at mærke vindpustet, inden det er, at de bare banker ind i min gain. Og jeg så er nødt til at sige. Jeg tror det er det. Jeg tror ikke, det har noget med evolution at gøre, Flemming. Det har jeg ikke skidt med. Det er fordi, de er for dumme. Det kan også være, at de har udviklet en eller anden form for religion omkring cyklister. Vi bliver hele tiden klogere på, at flere og flere dyr har en form for bevidsthed, end vi havde regnet med. På et eller andet tidspunkt erkender vi sikkert, at bananflugere også har bevidsthed og evnen til at skabe kultur. Måske ser de de her cyklister og tænker, at det her er Gud. Udfordret er en dansk videnskabskomik podcast medværterne Mark og Flemming. Du skal flyve ind i hulen, og så skal du kæmpe mod drøblen, og hvis du vinder, så bliver du en rigtig mand. Manddomsritual. Ja. Hvis du overlever at blive hostet ud igen, efter du er blevet slugt. Så får du lov til at lægge æg. Det tror jeg, det er det. Det tror jeg også. Der var den. Vi fandt den. Det tog lidt tid at komme det til, men vi kom det til. Og jeg kan se, at jeg lige har fået frem med Felix til at være med i moderatorgruppen. Nå ja, så kan det gå. Felix er ikke med i moderatorgruppen. Det er meget vigtigt, at I ved det. Det er kun Thijs. Okay. I skal kun sende det her til Thijs. Nå, på det måde. Ja, okay. Færdig nok. Så Jacob, vi håber, du kunne bruge det svar. Det er simpelthen, fordi det er en mandopsprøve. Udfordret er en dansk videnskabskomik podcast medværterne Mark og Flemming. Det er virkelig den mørke side af vanvittig verdenshistorie, I får lov til at opleve her. Jeg får e-mails, hvor i emnefeltet står der klageudrymstegn og står der tilrettet vedkommende. Vi Lindvang-kartellet ønsker at indgive en klage om vedrørende omtale af Felix Damm Nørgaard. Jeg synes også, de outerfolk, det er jeg ikke sikker på, at jeg har lyst til at sige efter navn. Er det som den person, vi lige har outet, eller hvad? Ja, i den seneste udgivelse af podcasten Vanvittig Verdens Story episode 77 omtales nævnte Felix Darm Nørgaard, igen med efternavn på efteråret, som moderator Felix. Dette er bagvæskelse og skadende for tidligere nævntes brand af Felix Darm Nørgaard kendte sig fansid Felix og ikke moderator Felix. Så Flemming, det kan du lære lidt af. Så okay, så vi har lige fået en klage til vanvittig verdenshistorie om, at han er blevet kaldt moderator. To minutter efter jeg har kaldt ham moderator. Jeg synes, du skal passe på med det der, Flemming. Så må de så sende en klage til vanvittig verdenshistorie om, at jeg har kaldt ham moderator også. Ja, og den er blevet underskrevet med ønsker om, at fejlen ikke gentages. Uvenligst. Lindvangs Good Times Society, TMAS. Udfordret er en dansk videnskabskomik podcast medværterne Mark og Flemming. Hvor fanden var den anden? Den var der. Jeg har fået en anden, hvor alle klagerne er sendt ind af den samme person. Og den her klage har emnefældet nudes på vegne af Moderatorgruppen TM. Vi vil gerne lige klage over, at de herre Peter Løde og Palæstinenser glemte at sende Moderatorgruppen TM selvportrætter og eller nudes, efter at have modtaget deres æresmedaljer ved gårdstabens begivenhed i Odense. Medaljerne blev givet efter fansiden havde afgjort, hvad de bedste aliaser var. Udvalgte moderatorer glemte at tage billeder under overrækkelsen og indgav efterfølgende en henstilling om, at værterne selv tog selfie med dem. Eventuelt nudes på foranledning af systemet. Har de ikke fået Peters nudes endnu? Nej, det ved jeg ikke. Men siger du, at jeg troede kun, at han sendte dem til mig? Nå, du har fået dem. Nu føler jeg, at kæft mand, han er sådan en fucking player. Men kan du ikke bare sende dem videre så, Flemming? Jo, men Mark, jeg er såret. Tænk lige på mine følelser. Er du klar over, hvad jeg har sendt ham billeder af på min krop? Nej. Så sidder han bare og sender alle mulige nudes videre til andre også. Undskyld, sender du billeder til ham? Du sender ikke engang billeder til mig? Jeg troede, jeg var noget særligt, jo. Du sender ikke engang billeder til mig? Nej, men du sender heller ikke nudes af Peter til mig. Men du sender heller ikke... Jeg forstår ikke det. Jeg har det meget dårligt med det nu. Hvorfor faktisk ikke? Åh herre. Vil du have mere Flemming? Ja. Jeg kan tilføje, at Felix nu er moderator for en gruppe, så nu er det hele i orden igen. Okay, klagevidrørende episode 78. Kære klageinstans, vi er forrettet. I episode 78 nævnte Alexander, at da Aarhus I var et søskendepark klar til at drikke kulæt. Vi i kulten føler os lidt trådt på, da de andre medlemmer også med glæde vil drikke både saftevand og offre mennesker for det kors. Især Felix og Maria føler sig overset, da de elsker, især elsker saftevand. Vendtis kultsekretariatet. Altså jeg ved ikke, hvad jeg skal sige andet end altså... Hør en ordentlig podcast i stedet for. Det har blevet en skæld udfordret. Altså, det fremgår jo tydeligt her, at vanvittig verdenshistorie er tydeligt. Altså, hvad er det for nogle mennesker? Jeg ved det ikke. Det er som om, de bare slet ikke gør noget for deres lyttere. Altså, helt ærligt. Det gør vi. Det gør vi. Vi gør mange ting for vores lyttere. Jeg tæsker Nikolaj hver eneste dag, inden jeg går i seng for jeres skyld. Jeg bliver så glad, når jeg hører det, Flemming. Okay, skal vi komme videre med den her outro? Ja tak. Skal vi få rated sidste uges afsnit? Så sidste uges afsnit har fået en samlet score på 67 fra os. Hvis I har lyst til at gå ind og rate, så kan I bare gøre det. Så rører det også ind og bliver en del af statistikken. En skor på 67 putter den ved vores afsnit om mord, hvor vi snakker om, hvordan man mest effektivt slipper afsted med at slå nogen ihjel uden at efterlade spor og kommer af med livet på en forsvarlig måde, f.eks. ved at fodre dem til krise. Er der noget, folk skal gøre, Mark? Det, I skal gøre den her uge, det er, at hvis I har lyst, og også hvis I ikke har lyst, så kan I gå ind og vælge at støtte os på. Udfordret er en dansk videnskabskomik podcast medværterne Mark og Flemming. Jeg tror, hvis man støtter med en krone, så er det sådan noget med, at den skal minimum trække to kroner eller sådan noget, for at det giver mening. Så en krone, så trækker den hver anden måned, tror jeg. Men jeg er ikke helt sikker. Men altså, man kan støtte, hvad man vil. Og så får man også adgang til vores Discord, og man får adgang til et Google-drev, hvor vi har alle mulige ekstra materiale og alle mulige gode sager på Discord. Jamen, der er ikke noget inde på det drive der, Mark. Det er der ikke. Altså, der sidder vel 15 af 13 foruden os, der bare lytter med og har det fedt lige nu. Så kom og vær med. Det er bots. I skal ikke høre, hvad han siger. Hvis jeg har nogen klager, så send dem til vanvittig verdenshistorie. Sørg for at sende dem en hel masse. Ja. Hvad med næste uges afsnit, Flemming? Næste uges afsnit skal handle om en økonom, der har lært aber at bruge penge. Det er meget on brand med dig. Jeg tænkte, jeg måske selv kunne lære det ved at kigge, hvordan han lærte aberne det. Så var det ligesom udgangspunkt. Hvis de kunne, så kunne jeg nok også godt. Nå, jeg troede, du ville lære den hønste videre. Men jeg kan godt se, at du selvfølgelig selv skal lære det først. Det er klart. Okay, spændende. Det glæder jeg mig meget til. Har du en dyrfakt til mig, Mark? Det har jeg. Det kan jeg love dig for. Dagens dyrfakt er sendt ind af Thijs, som han sidder også med på Discord lige nu. Det er rigtig dejligt. Hej, Thijs. Thijs har skrevet ind, at finkeunger, altså fuglen, fingten, ungerne derfra, de har tegninger i munden, og ingen ved hvorfor. Tegninger i munden? Det er simpelthen tegninger. De har simpelthen former og figurer inde i deres mund, som er tegnet på deres næb, og ingen ved hvorfor. Der er Gudfindens Intelligent Design Folkens. Intelligent Design. Tak fordi I lyttede med. Jeg har været jeres vært og smør til øregang i dag, Flemming. Jeg har været jeres dårlig luft og drikbare afføring, Mark. Tak fordi I lyttede med. Husk at være dumme.","dyrfakt":"Finkeunger har tegninger i munden, og ingen ved hvorfor.","listener_question":null}